henson_sentry.py
Henson_Sentry-0.4.0.dist-info/DESCRIPTION.rst
Henson_Sentry-0.4.0.dist-info/METADATA
Henson_Sentry-0.4.0.dist-info/RECORD
Henson_Sentry-0.4.0.dist-info/WHEEL
Henson_Sentry-0.4.0.dist-info/metadata.json
Henson_Sentry-0.4.0.dist-info/top_level.txt
