Metadata-Version: 2.0
Name: Henson-Sentry
Version: 0.4.0
Summary: A library for integrating Sentry into a Henson application
Home-page: https://henson-sentry.readthedocs.io
Author: Andy Dirnberger, Leonard Bedner, and others
Author-email: henson@iheart.com
License: MIT
Platform: UNKNOWN
Classifier: Development Status :: 4 - Beta
Classifier: Intended Audience :: Developers
Classifier: License :: OSI Approved :: MIT License
Classifier: Operating System :: OS Independent
Classifier: Programming Language :: Python
Classifier: Programming Language :: Python :: 3.8
Classifier: Programming Language :: Python :: 3.9
Classifier: Programming Language :: Python :: 3 :: Only
Classifier: Topic :: Software Development
Requires-Dist: Henson
Requires-Dist: raven-aiohttp
